roverio/__init__.py
roverio/constants.py
roverio/file_extension.py
roverio/phone_email_searcher.py
roverio/py.typed
roverio/readmy_readmes.py
roverio/scout.py
roverio/secrets.py
roverio/sequential_renamer.py
test/__init__.py
roverio-2.3.1.dist-info/LICENSE
roverio-2.3.1.dist-info/METADATA
roverio-2.3.1.dist-info/WHEEL
roverio-2.3.1.dist-info/entry_points.txt
roverio-2.3.1.dist-info/top_level.txt
roverio-2.3.1.dist-info/RECORD
