Metadata-Version: 2.1
Name: roverio
Version: 2.3.1
Summary: Rover IO is a suite of tools that traverses your directories and performs IO file operations.
Home-page: http://github.com/justintime50/roverio
Author: Justintime50
License: MIT
Platform: UNKNOWN
Classifier: Programming Language :: Python :: 3
Classifier: License :: OSI Approved :: MIT License
Classifier: Operating System :: OS Independent
Requires-Python: >=3.7, <4
License-File: LICENSE
Requires-Dist: pretty-tables (==2.*)
Provides-Extra: dev
Requires-Dist: black ; extra == 'dev'
Requires-Dist: coveralls (==3.*) ; extra == 'dev'
Requires-Dist: flake8 ; extra == 'dev'
Requires-Dist: isort ; extra == 'dev'
Requires-Dist: mypy ; extra == 'dev'
Requires-Dist: pytest (==6.*) ; extra == 'dev'
Requires-Dist: pytest-cov (==2.*) ; extra == 'dev'
